netrun_sim-0.1.1.dist-info/METADATA
netrun_sim-0.1.1.dist-info/WHEEL
netrun_sim/__init__.py
netrun_sim/__init__.pyi
netrun_sim/netrun_sim.abi3.so
netrun_sim/py.typed
netrun_sim-0.1.1.dist-info/RECORD
