Metadata-Version: 2.4
Name: netrun-sim
Version: 0.1.1
Classifier: Programming Language :: Rust
Classifier: Programming Language :: Python :: Implementation :: CPython
Requires-Dist: python-ulid>=1.0
Requires-Python: >=3.8
